{
  "__inputs": [
    {
      "name": "DS_PROMETHEUS",
      "label": "prometheus",
      "description": "",
      "type": "datasource",
      "pluginId": "prometheus",
      "pluginName": "Prometheus"
    }
  ],
  "__requires": [
    {
      "type": "grafana",
      "id": "grafana",
      "name": "Grafana",
      "version": "6.1.6"
    },
    {
      "type": "panel",
      "id": "graph",
      "name": "Graph",
      "version": ""
    },
    {
      "type": "datasource",
      "id": "prometheus",
      "name": "Prometheus",
      "version": "1.0.0"
    },
    {
      "type": "panel",
      "id": "table",
      "name": "Table",
      "version": ""
    }
  ],
  "annotations": {
    "list": [
      {
        "builtIn": 1,
        "datasource": "-- Grafana --",
        "enable": true,
        "hide": true,
        "iconColor": "rgba(0, 211, 255, 1)",
        "name": "Annotations & Alerts",
        "type": "dashboard"
      }
    ]
  },
  "description": "Smartmon Texfile node_exporter Dashboard",
  "editable": true,
  "gnetId": 3992,
  "graphTooltip": 0,
  "id": null,
  "iteration": 1569781955199,
  "links": [],
  "panels": [
    {
      "columns": [],
      "datasource": "$datasource",
      "fontSize": "100%",
      "gridPos": {
        "h": 6,
        "w": 24,
        "x": 0,
        "y": 0
      },
      "height": "170px",
      "id": 4,
      "links": [],
      "pageSize": null,
      "scroll": true,
      "showHeader": true,
      "sort": {
        "col": 0,
        "desc": true
      },
      "styles": [
        {
          "alias": "Time",
          "dateFormat": "YYYY-MM-DD HH:mm:ss",
          "pattern": "Time",
          "type": "date"
        },
        {
          "alias": "Disk",
          "colorMode": null,
          "colors": [
            "rgba(245, 54, 54, 0.9)",
            "rgba(237, 129, 40, 0.89)",
            "rgba(50, 172, 45, 0.97)"
          ],
          "dateFormat": "YYYY-MM-DD HH:mm:ss",
          "decimals": 2,
          "mappingType": 1,
          "pattern": "disk",
          "thresholds": [],
          "type": "string",
          "unit": "none"
        },
        {
          "alias": "",
          "colorMode": null,
          "colors": [
            "rgba(245, 54, 54, 0.9)",
            "rgba(237, 129, 40, 0.89)",
            "rgba(50, 172, 45, 0.97)"
          ],
          "decimals": 2,
          "pattern": "type",
          "thresholds": [],
          "type": "string",
          "unit": "short"
        },
        {
          "alias": "",
          "colorMode": null,
          "colors": [
            "rgba(245, 54, 54, 0.9)",
            "rgba(237, 129, 40, 0.89)",
            "rgba(50, 172, 45, 0.97)"
          ],
          "dateFormat": "YYYY-MM-DD HH:mm:ss",
          "decimals": 2,
          "mappingType": 1,
          "pattern": "/.*/",
          "thresholds": [],
          "type": "hidden",
          "unit": "short"
        }
      ],
      "targets": [
        {
          "expr": "smartmon_device_smart_healthy{instance=~\"$instance\"} < 1",
          "format": "table",
          "interval": "2m",
          "intervalFactor": 2,
          "legendFormat": "",
          "refId": "A"
        }
      ],
      "title": "SMART Unhealthy Disks",
      "transform": "table",
      "type": "table"
    },
    {
      "aliasColors": {},
      "bars": false,
      "dashLength": 10,
      "dashes": false,
      "datasource": "$datasource",
      "decimals": null,
      "fill": 0,
      "gridPos": {
        "h": 10,
        "w": 12,
        "x": 0,
        "y": 6
      },
      "id": 1,
      "legend": {
        "alignAsTable": true,
        "avg": true,
        "current": true,
        "max": true,
        "min": true,
        "rightSide": false,
        "show": true,
        "sideWidth": null,
        "total": false,
        "values": true
      },
      "lines": false,
      "linewidth": 1,
      "links": [],
      "nullPointMode": "null",
      "percentage": false,
      "pointradius": 1,
      "points": true,
      "renderer": "flot",
      "seriesOverrides": [],
      "spaceLength": 10,
      "stack": false,
      "steppedLine": false,
      "targets": [
        {
          "expr": "avg(smartmon_temperature_celsius_cel_value{instance=~\"$instance\"}) by (instance, disk)",
          "format": "time_series",
          "hide": false,
          "interval": "2m",
          "intervalFactor": 2,
          "legendFormat": "val {{instance}} {{disk}}",
          "refId": "B"
        },
        {
          "expr": "avg(smartmon_temperature_celsius_raw_value{instance=~\"$instance\"}or smartmon_airflow_temperature_cel_raw_value) by (instance, disk)",
          "format": "time_series",
          "hide": false,
          "interval": "2m",
          "intervalFactor": 2,
          "legendFormat": "raw {{instance}} {{disk}}",
          "refId": "A"
        }
      ],
      "thresholds": [],
      "timeFrom": null,
      "timeRegions": [],
      "timeShift": null,
      "title": "Disk Temperature",
      "tooltip": {
        "shared": true,
        "sort": 0,
        "value_type": "individual"
      },
      "type": "graph",
      "xaxis": {
        "buckets": null,
        "mode": "time",
        "name": null,
        "show": true,
        "values": []
      },
      "yaxes": [
        {
          "format": "short",
          "label": null,
          "logBase": 1,
          "max": null,
          "min": null,
          "show": true
        },
        {
          "format": "short",
          "label": null,
          "logBase": 1,
          "max": null,
          "min": null,
          "show": true
        }
      ],
      "yaxis": {
        "align": false,
        "alignLevel": null
      }
    },
    {
      "aliasColors": {},
      "bars": false,
      "dashLength": 10,
      "dashes": false,
      "datasource": "$datasource",
      "decimals": null,
      "fill": 0,
      "gridPos": {
        "h": 10,
        "w": 12,
        "x": 12,
        "y": 6
      },
      "id": 7,
      "legend": {
        "alignAsTable": true,
        "avg": true,
        "current": true,
        "max": true,
        "min": true,
        "rightSide": false,
        "show": true,
        "sideWidth": null,
        "total": false,
        "values": true
      },
      "lines": false,
      "linewidth": 1,
      "links": [],
      "nullPointMode": "null",
      "percentage": false,
      "pointradius": 1,
      "points": true,
      "renderer": "flot",
      "seriesOverrides": [],
      "spaceLength": 10,
      "stack": false,
      "steppedLine": false,
      "targets": [
        {
          "expr": "avg(smartmon_airflow_temperature_cel_value{instance=~\"$instance\"}) by (instance, disk)",
          "format": "time_series",
          "hide": false,
          "interval": "2m",
          "intervalFactor": 2,
          "legendFormat": "val {{instance}} {{disk}}",
          "refId": "B"
        },
        {
          "expr": "avg(smartmon_airflow_temperature_cel_raw_value{instance=~\"$instance\"}or smartmon_airflow_temperature_cel_raw_value) by (instance, disk)",
          "format": "time_series",
          "hide": false,
          "interval": "2m",
          "intervalFactor": 2,
          "legendFormat": "raw {{instance}} {{disk}}",
          "refId": "A"
        }
      ],
      "thresholds": [],
      "timeFrom": null,
      "timeRegions": [],
      "timeShift": null,
      "title": "Disk Airflow Temperature",
      "tooltip": {
        "shared": true,
        "sort": 0,
        "value_type": "individual"
      },
      "type": "graph",
      "xaxis": {
        "buckets": null,
        "mode": "time",
        "name": null,
        "show": true,
        "values": []
      },
      "yaxes": [
        {
          "format": "short",
          "label": null,
          "logBase": 1,
          "max": null,
          "min": null,
          "show": true
        },
        {
          "format": "short",
          "label": null,
          "logBase": 1,
          "max": null,
          "min": null,
          "show": true
        }
      ],
      "yaxis": {
        "align": false,
        "alignLevel": null
      }
    },
    {
      "aliasColors": {},
      "bars": false,
      "dashLength": 10,
      "dashes": false,
      "datasource": "$datasource",
      "fill": 1,
      "gridPos": {
        "h": 7,
        "w": 12,
        "x": 0,
        "y": 16
      },
      "id": 2,
      "legend": {
        "alignAsTable": true,
        "avg": true,
        "current": true,
        "max": true,
        "min": true,
        "rightSide": true,
        "show": true,
        "total": false,
        "values": true
      },
      "lines": true,
      "linewidth": 1,
      "links": [],
      "nullPointMode": "null",
      "percentage": false,
      "pointradius": 5,
      "points": false,
      "renderer": "flot",
      "seriesOverrides": [],
      "spaceLength": 10,
      "stack": false,
      "steppedLine": false,
      "targets": [
        {
          "expr": "avg(smartmon_raw_read_error_rate_value{instance=~\"$instance\"}) by (instance, disk)",
          "format": "time_series",
          "interval": "2m",
          "intervalFactor": 2,
          "legendFormat": "val {{instance}} {{disk}}",
          "refId": "A"
        },
        {
          "expr": "avg(smartmon_spin_retry_count_raw_value{instance=~\"$instance\"}) by (instance, disk)",
          "format": "time_series",
          "interval": "2m",
          "intervalFactor": 2,
          "legendFormat": "raw {{instance}} {{disk}}",
          "refId": "B"
        }
      ],
      "thresholds": [],
      "timeFrom": null,
      "timeRegions": [],
      "timeShift": null,
      "title": "Raw Error Read Rate",
      "tooltip": {
        "shared": true,
        "sort": 0,
        "value_type": "individual"
      },
      "type": "graph",
      "xaxis": {
        "buckets": null,
        "mode": "time",
        "name": null,
        "show": true,
        "values": []
      },
      "yaxes": [
        {
          "format": "short",
          "label": null,
          "logBase": 1,
          "max": null,
          "min": null,
          "show": true
        },
        {
          "format": "short",
          "label": null,
          "logBase": 1,
          "max": null,
          "min": null,
          "show": true
        }
      ],
      "yaxis": {
        "align": false,
        "alignLevel": null
      }
    },
    {
      "aliasColors": {},
      "bars": false,
      "dashLength": 10,
      "dashes": false,
      "datasource": "$datasource",
      "fill": 1,
      "gridPos": {
        "h": 7,
        "w": 12,
        "x": 12,
        "y": 16
      },
      "id": 3,
      "legend": {
        "alignAsTable": true,
        "avg": true,
        "current": true,
        "max": true,
        "min": true,
        "rightSide": true,
        "show": true,
        "total": false,
        "values": true
      },
      "lines": true,
      "linewidth": 1,
      "links": [],
      "nullPointMode": "null",
      "percentage": false,
      "pointradius": 5,
      "points": false,
      "renderer": "flot",
      "seriesOverrides": [],
      "spaceLength": 10,
      "stack": false,
      "steppedLine": false,
      "targets": [
        {
          "expr": "avg(smartmon_total_lbas_written_value{instance=~\"$instance\"}) by (instance, disk)",
          "format": "time_series",
          "interval": "2m",
          "intervalFactor": 2,
          "legendFormat": "val {{instance}} {{disk}}",
          "refId": "A"
        },
        {
          "expr": "avg(smartmon_total_lbas_written_raw_value{instance=~\"$instance\"}) by (instance, disk)",
          "format": "time_series",
          "interval": "2m",
          "intervalFactor": 2,
          "legendFormat": "raw {{instance}} {{disk}}",
          "refId": "B"
        }
      ],
      "thresholds": [],
      "timeFrom": null,
      "timeRegions": [],
      "timeShift": null,
      "title": "Raw Error Read Rate",
      "tooltip": {
        "shared": true,
        "sort": 0,
        "value_type": "individual"
      },
      "type": "graph",
      "xaxis": {
        "buckets": null,
        "mode": "time",
        "name": null,
        "show": true,
        "values": []
      },
      "yaxes": [
        {
          "format": "short",
          "label": null,
          "logBase": 1,
          "max": null,
          "min": null,
          "show": true
        },
        {
          "format": "short",
          "label": null,
          "logBase": 1,
          "max": null,
          "min": null,
          "show": true
        }
      ],
      "yaxis": {
        "align": false,
        "alignLevel": null
      }
    },
    {
      "aliasColors": {},
      "bars": false,
      "dashLength": 10,
      "dashes": false,
      "datasource": "$datasource",
      "fill": 1,
      "gridPos": {
        "h": 7,
        "w": 12,
        "x": 0,
        "y": 23
      },
      "id": 5,
      "legend": {
        "alignAsTable": true,
        "avg": true,
        "current": true,
        "max": true,
        "min": true,
        "rightSide": true,
        "show": true,
        "total": false,
        "values": true
      },
      "lines": true,
      "linewidth": 1,
      "links": [],
      "nullPointMode": "null",
      "percentage": false,
      "pointradius": 5,
      "points": false,
      "renderer": "flot",
      "seriesOverrides": [],
      "spaceLength": 10,
      "stack": false,
      "steppedLine": false,
      "targets": [
        {
          "expr": "smartmon_reallocated_sector_ct_raw_value{instance=~\"$instance\"}",
          "format": "time_series",
          "interval": "2m",
          "intervalFactor": 2,
          "legendFormat": "raw {{instance}} {{disk}}",
          "refId": "B"
        },
        {
          "expr": "smartmon_reallocated_sector_ct_value{instance=~\"$instance\"}",
          "format": "time_series",
          "interval": "2m",
          "intervalFactor": 2,
          "legendFormat": "val {{instance}} {{disk}}",
          "refId": "A"
        }
      ],
      "thresholds": [],
      "timeFrom": null,
      "timeRegions": [],
      "timeShift": null,
      "title": "Reallocated Sectors",
      "tooltip": {
        "shared": true,
        "sort": 0,
        "value_type": "individual"
      },
      "type": "graph",
      "xaxis": {
        "buckets": null,
        "mode": "time",
        "name": null,
        "show": true,
        "values": []
      },
      "yaxes": [
        {
          "format": "short",
          "label": null,
          "logBase": 1,
          "max": null,
          "min": "0",
          "show": true
        },
        {
          "format": "short",
          "label": null,
          "logBase": 1,
          "max": null,
          "min": null,
          "show": true
        }
      ],
      "yaxis": {
        "align": false,
        "alignLevel": null
      }
    },
    {
      "aliasColors": {},
      "bars": false,
      "dashLength": 10,
      "dashes": false,
      "datasource": "$datasource",
      "fill": 1,
      "gridPos": {
        "h": 7,
        "w": 12,
        "x": 12,
        "y": 23
      },
      "id": 6,
      "legend": {
        "alignAsTable": true,
        "avg": true,
        "current": true,
        "max": true,
        "min": true,
        "rightSide": true,
        "show": true,
        "total": false,
        "values": true
      },
      "lines": true,
      "linewidth": 1,
      "links": [],
      "nullPointMode": "null",
      "percentage": false,
      "pointradius": 5,
      "points": false,
      "renderer": "flot",
      "seriesOverrides": [],
      "spaceLength": 10,
      "stack": false,
      "steppedLine": false,
      "targets": [
        {
          "expr": "smartmon_current_pending_sector_raw_value{instance=~\"$instance\"}",
          "format": "time_series",
          "interval": "2m",
          "intervalFactor": 2,
          "legendFormat": "raw {{instance}} {{disk}}",
          "refId": "B"
        },
        {
          "expr": "smartmon_current_pending_sector_value{instance=~\"$instance\"}",
          "format": "time_series",
          "interval": "2m",
          "intervalFactor": 2,
          "legendFormat": "val {{instance}} {{disk}}",
          "refId": "A"
        }
      ],
      "thresholds": [],
      "timeFrom": null,
      "timeRegions": [],
      "timeShift": null,
      "title": "Current Pending Sectors",
      "tooltip": {
        "shared": true,
        "sort": 0,
        "value_type": "individual"
      },
      "type": "graph",
      "xaxis": {
        "buckets": null,
        "mode": "time",
        "name": null,
        "show": true,
        "values": []
      },
      "yaxes": [
        {
          "format": "short",
          "label": null,
          "logBase": 1,
          "max": null,
          "min": "0",
          "show": true
        },
        {
          "format": "short",
          "label": null,
          "logBase": 1,
          "max": null,
          "min": null,
          "show": true
        }
      ],
      "yaxis": {
        "align": false,
        "alignLevel": null
      }
    }
  ],
  "schemaVersion": 18,
  "style": "dark",
  "tags": [
    "prometheus",
    "node_exporter",
    "smartmon",
    "textfile"
  ],
  "templating": {
    "list": [
      {
        "current": {
          "text": "prometheus",
          "value": "prometheus"
        },
        "hide": 0,
        "includeAll": false,
        "label": null,
        "multi": false,
        "name": "datasource",
        "options": [],
        "query": "prometheus",
        "refresh": 1,
        "regex": "",
        "skipUrlSync": false,
        "type": "datasource"
      },
      {
        "allValue": null,
        "current": {},
        "datasource": "${DS_PROMETHEUS}",
        "definition": "",
        "hide": 0,
        "includeAll": true,
        "label": null,
        "multi": true,
        "name": "instance",
        "options": [],
        "query": "label_values(smartmon_smartctl_version, instance)",
        "refresh": 1,
        "regex": "",
        "skipUrlSync": false,
        "sort": 1,
        "tagValuesQuery": "",
        "tags": [],
        "tagsQuery": "",
        "type": "query",
        "useTags": false
      }
    ]
  },
  "time": {
    "from": "now-24h",
    "to": "now"
  },
  "timepicker": {
    "refresh_intervals": [
      "5s",
      "10s",
      "30s",
      "1m",
      "5m",
      "15m",
      "30m",
      "1h",
      "2h",
      "1d"
    ],
    "time_options": [
      "5m",
      "15m",
      "1h",
      "6h",
      "12h",
      "24h",
      "2d",
      "7d",
      "30d"
    ]
  },
  "timezone": "browser",
  "title": "Smartmon Textfile",
  "uid": "zCGPPqtWk",
  "version": 6
}
